[
    {
    "id": 1,
    "name": "Leanne Graham",
    "img": "https://i.ibb.co/BGbKJ9T/Heb24efe777a14a92a89a27c3320fe49d4-jpg-220x220.webp",
    "price": "20",
    "moq": "15",
    "available": "35"
       },
    {
    "id": 2,
    "name": "Leanne Graham",
    "img": "https://i.ibb.co/BGbKJ9T/Heb24efe777a14a92a89a27c3320fe49d4-jpg-220x220.webp",
    "price": "20",
    "moq": "15",
    "available": "35"
       },
    {
    "id": 3,
    "name": "Leanne Graham",
    "img": "https://i.ibb.co/BGbKJ9T/Heb24efe777a14a92a89a27c3320fe49d4-jpg-220x220.webp",
    "price": "20",
    "moq": "15",
    "available": "35"
       },
    {
    "id": 4,
    "name": "Leanne Graham",
    "img": "https://i.ibb.co/BGbKJ9T/Heb24efe777a14a92a89a27c3320fe49d4-jpg-220x220.webp",
    "price": "20",
    "moq": "15",
    "available": "35"
       },
    {
    "id": 5,
    "name": "Leanne Graham",
    "img": "https://i.ibb.co/BGbKJ9T/Heb24efe777a14a92a89a27c3320fe49d4-jpg-220x220.webp",
    "price": "20",
    "moq": "15",
    "available": "35"
       },
    {
    "id": 6,
    "name": "Leanne Graham",
    "img": "https://i.ibb.co/BGbKJ9T/Heb24efe777a14a92a89a27c3320fe49d4-jpg-220x220.webp",
    "price": "20",
    "moq": "15",
    "available": "35"
       },
    {
    "id": 7,
    "name": "Leanne Graham",
    "img": "https://i.ibb.co/BGbKJ9T/Heb24efe777a14a92a89a27c3320fe49d4-jpg-220x220.webp",
    "price": "20",
    "moq": "15",
    "available": "35"
       }
    ]